<annotation>
	<folder>image</folder>
	<filename>001935.png</filename>
	<path>D:\Data\DataGenerator\data\test\training\image\001935.png</path>
	<source>
		<database>Unknown</database>
	</source>
	<size>
		<width>1080</width>
		<height>720</height>
		<depth>3</depth>
	</size>
	<segmented>0</segmented>
	<object>
		<name>RoadSign_forward_left</name>
		<pose>Unspecified</pose>
		<truncated>0</truncated>
		<difficult>0</difficult>
		<bndbox>
			<xmin>502</xmin>
			<ymin>408</ymin>
			<xmax>571</xmax>
			<ymax>431</ymax>
		</bndbox>
	</object>
	<object>
		<name>RoadSign_forward</name>
		<pose>Unspecified</pose>
		<truncated>0</truncated>
		<difficult>0</difficult>
		<bndbox>
			<xmin>641</xmin>
			<ymin>409</ymin>
			<xmax>689</xmax>
			<ymax>433</ymax>
		</bndbox>
	</object>
</annotation>
