<annotation>
	<folder>image</folder>
	<filename>002510.png</filename>
	<path>D:\Data\DataGenerator\data\test\training\image\002510.png</path>
	<source>
		<database>Unknown</database>
	</source>
	<size>
		<width>1080</width>
		<height>720</height>
		<depth>3</depth>
	</size>
	<segmented>0</segmented>
	<object>
		<name>TrafficLight</name>
		<pose>Unspecified</pose>
		<truncated>0</truncated>
		<difficult>0</difficult>
		<bndbox>
			<xmin>721</xmin>
			<ymin>259</ymin>
			<xmax>734</xmax>
			<ymax>283</ymax>
		</bndbox>
	</object>
	<object>
		<name>TrafficLight</name>
		<pose>Unspecified</pose>
		<truncated>0</truncated>
		<difficult>0</difficult>
		<bndbox>
			<xmin>748</xmin>
			<ymin>244</ymin>
			<xmax>767</xmax>
			<ymax>272</ymax>
		</bndbox>
	</object>
	<object>
		<name>TrafficLight</name>
		<pose>Unspecified</pose>
		<truncated>0</truncated>
		<difficult>0</difficult>
		<bndbox>
			<xmin>784</xmin>
			<ymin>231</ymin>
			<xmax>800</xmax>
			<ymax>258</ymax>
		</bndbox>
	</object>
</annotation>
